pygeodes/__init__.py
pygeodes/_info.py
pygeodes/cli/__init__.py
pygeodes/cli/argparser.py
pygeodes/cli/cli.py
pygeodes/cli/cli_utils.py
pygeodes/data/__init__.py
pygeodes/data/model.json
pygeodes/geodes.py
pygeodes/utils/__init__.py
pygeodes/utils/config.py
pygeodes/utils/consts.py
pygeodes/utils/dataclasses_utils.py
pygeodes/utils/datetime_utils.py
pygeodes/utils/decorators.py
pygeodes/utils/download.py
pygeodes/utils/exceptions.py
pygeodes/utils/formatting.py
pygeodes/utils/io.py
pygeodes/utils/logger.py
pygeodes/utils/processing.py
pygeodes/utils/profile.py
pygeodes/utils/query.py
pygeodes/utils/request.py
pygeodes/utils/s3.py
pygeodes/utils/stac.py
pygeodes-0.1.5.dist-info/METADATA
pygeodes-0.1.5.dist-info/WHEEL
pygeodes-0.1.5.dist-info/entry_points.txt
pygeodes-0.1.5.dist-info/licenses/LICENSE
pygeodes-0.1.5.dist-info/RECORD
