Metadata-Version: 2.4
Name: pygeodes
Version: 0.1.5
Summary: A Python client for Geodes APIs
License: MIT
License-File: LICENSE
Author: CNES
Requires-Python: >=3.10
Classifier: License :: OSI Approved :: MIT License
Classifier: Programming Language :: Python :: 3
Classifier: Programming Language :: Python :: 3.10
Classifier: Programming Language :: Python :: 3.11
Classifier: Programming Language :: Python :: 3.12
Classifier: Programming Language :: Python :: 3.13
Classifier: Programming Language :: Python :: 3.14
Requires-Dist: aiofiles (>=24.1.0,<25.0.0)
Requires-Dist: aiohttp (>=3.9.5,<4.0.0)
Requires-Dist: boto3 (>=1.34.142,<2.0.0)
Requires-Dist: folium (>=0.17.0,<0.18.0)
Requires-Dist: geopandas (>=1.0,<2.0)
Requires-Dist: ipython (==8.12.3)
Requires-Dist: pandas (>=2.2,<3.0)
Requires-Dist: pystac (==1.8.0)
Requires-Dist: remotezip (>=0.12.3,<0.13.0)
Requires-Dist: requests (>=2.32.3,<3.0.0)
Requires-Dist: rich (>=13.7.1,<14.0.0)
Requires-Dist: tqdm (>=4.66.4,<5.0.0)
Requires-Dist: validators (>=0.28.3,<0.29.0)
Requires-Dist: whoosh (>=2.7.4,<3.0.0)
Project-URL: Homepage, https://geodes.cnes.fr
Project-URL: Repository, https://github.com/CNES/pyGeodes
